cutelog/__init__.py
cutelog/__main__.py
cutelog/about_dialog.py
cutelog/config.py
cutelog/level_edit_dialog.py
cutelog/levels_preset_dialog.py
cutelog/listener.py
cutelog/log_levels.py
cutelog/logger_tab.py
cutelog/logger_table_header.py
cutelog/main_window.py
cutelog/merge_dialog.py
cutelog/pop_in_dialog.py
cutelog/resources.py
cutelog/settings_dialog.py
cutelog/text_view_dialog.py
cutelog/utils.py
cutelog-2.2.0.data/data/share/applications/cutelog.desktop
cutelog-2.2.0.data/data/share/pixmaps/cutelog.png
cutelog-2.2.0.dist-info/LICENSE
cutelog-2.2.0.dist-info/METADATA
cutelog-2.2.0.dist-info/WHEEL
cutelog-2.2.0.dist-info/entry_points.txt
cutelog-2.2.0.dist-info/top_level.txt
cutelog-2.2.0.dist-info/RECORD
