Metadata-Version: 2.1
Name: cutelog
Version: 2.2.0
Summary: GUI for Python's logging module
Home-page: https://github.com/busimus/cutelog/
Download-URL: https://github.com/Busimus/cutelog/archive/2.2.0.zip
Author: Alexander Bus
Author-email: busfromrus@gmail.com
License: MIT
Keywords: log,logging,gui,qt
Classifier: Development Status :: 4 - Beta
Classifier: Environment :: X11 Applications :: Qt
Classifier: Environment :: MacOS X :: Cocoa
Classifier: Environment :: Win32 (MS Windows)
Classifier: Intended Audience :: Developers
Classifier: Intended Audience :: System Administrators
Classifier: License :: OSI Approved :: MIT License
Classifier: Operating System :: POSIX :: Linux
Classifier: Programming Language :: Python
Classifier: Programming Language :: Python :: 3.5
Classifier: Programming Language :: Python :: 3 :: Only
Classifier: Topic :: Software Development :: Quality Assurance
Classifier: Topic :: System :: Logging
Classifier: Topic :: System :: Monitoring
Requires-Python: >=3.5
License-File: LICENSE
Requires-Dist: QtPy
Requires-Dist: jsonstream (==0.0.1)
Requires-Dist: PyQt5 ; platform_system == "Darwin"
Requires-Dist: PyQt5 ; platform_system == "Windows"
